{"generated":"2026-03-21T21:47:04.512317+00:00","period_start":"2026-03-15T20:00:00+00:00","period_end":"2026-03-21T21:27:00+00:00","snapshot_count":90,"html":"<h1>THE VENDETTA GAZETTE</h1>\n<h2>EXCLUSIVE EDITION — March 21, 2026 — \"All The News That Bleeds, We Print\"</h2>\n\n<h3>TERRITORY TITANS TEAR UP THE TURF!</h3>\n<h3>Sir Caprice and Wu-Tang the Dragon Lock Horns in Bloodiest Week Yet</h3>\n\n<p><strong>VENDETTA CITY</strong> — The cobblestones ran red with bootlegger blood this week as two criminal colossi carved up the city like a Thanksgiving turkey! In a spectacular display of underworld ambition, the dapper don known as <strong>Sir Caprice</strong> and the mysterious Oriental mastermind <strong>Wu-Tang the Dragon</strong> have painted the town crimson, claiming a staggering 195 territories between them in seven days of mayhem that would make Al Capone himself tip his fedora in respect.</p>\n\n<p>Sir Caprice, that silver-tongued serpent of the society set, slithered his way to the top of the heap with <em>98 freshly conquered turfs</em>, leaving a trail of demolished headquarters in his wake. Not to be outdone, Wu-Tang the Dragon breathed fire across the Eastern territories, snatching <em>97 prime pieces of real estate</em> with the precision of a master assassin and the fury of a typhoon.</p>\n\n<p>But hold onto your hip flasks, dear readers — the carnage doesn't end there! <strong>Vacation Steve</strong>, that sun-kissed scoundrel who supposedly operates his empire from a beach chair, managed to muscle his way into 48 new territories while sipping gin rickeys. His partner in paradise, <strong>Vacation Albert</strong>, wasn't far behind with 40 turfs of his own, proving that crime doesn't take a holiday when there's serious scratch to be made.</p>\n\n<p>Meanwhile, the crimson-cloaked <strong>Blood Captain</strong> lived up to his sanguinary sobriquet, spilling just enough claret to claim 28 choice chunks of city blocks. Even the controversial kingpin <strong>Donald Trump</strong> managed to trump his competition, seizing 20 territories with his usual bombastic flair.</p>\n\n<blockquote>\n<strong>SPECIAL BULLETIN!</strong><br>\n<em>HEADQUARTERS HELL!</em><br><br>\nThe most spectacular storming of the week belonged to <strong>Wu-Tang the Dragon</strong>, who demonstrated why they call him the <em>\"Scourge of the East Side\"</em> by obliterating a staggering <strong>17 rival headquarters</strong>! Not content with mere territorial expansion, this Oriental overlord turned enemy strongholds into smoking ruins faster than a Tommy gun empties its drum. Sir Caprice, never one to be upstaged, answered with 13 headquarters of his own, turning Vendetta City into a veritable demolition derby of criminal real estate!\n</blockquote>\n\n<p>But for every king, there must be casualties in this chess game of crime. <strong>StreetKing</strong>, once the undisputed monarch of the avenues, found his crown considerably tarnished as he hemorrhaged 27 territories to hungrier hoodlums. The grandiose <strong>FIFTH BLOOD EMPEROR</strong> discovered that imperial titles mean little when the bullets start flying, losing 22 of his precious principalities to more aggressive adversaries.</p>\n\n<p>The mysterious <strong>vortex</strong> got sucked into a whirlpool of his own making, watching 21 turfs disappear faster than bathtub gin at a police raid. <strong>Ustaz Ice</strong>, that cold-blooded calculator of crime, found his operations melting under pressure as 21 territories slipped through his frostbitten fingers.</p>\n\n<p>This week's violence netted the victorious villains over <em>$28,000 in cold hard cash</em> and enough artillery to arm a small revolution. Wu-Tang the Dragon led the looting parade with 120 raids, followed closely by Sir Caprice's 113 sorties into enemy territory.</p>\n\n<hr>\n<svg xmlns=\"http://www.w3.org/2000/svg\" width=\"640\" height=\"276\" style=\"font-family:Georgia,serif;background:#0a0800;display:block;margin:18px auto\">\n<text x=\"320\" y=\"22\" text-anchor=\"middle\" fill=\"#c8a84a\" font-size=\"13\" font-weight=\"bold\" letter-spacing=\"2\" font-family=\"Georgia,serif\">TERRITORY GAINS THIS WEEK</text>\n<line x1=\"20\" y1=\"28\" x2=\"620\" y2=\"28\" stroke=\"#3a2a00\" stroke-width=\"1\"/>\n<text x=\"154\" y=\"48\" text-anchor=\"end\" fill=\"#a09060\" font-size=\"11\" font-family=\"Georgia,serif\">Sir Caprice</text>\n<rect x=\"160\" y=\"35\" width=\"400\" height=\"16\" fill=\"#c8a84a\" opacity=\"0.85\"/>\n<text x=\"566\" y=\"48\" fill=\"#c8a84a\" font-size=\"11\" font-family=\"Georgia,serif\">+98</text>\n<text x=\"154\" y=\"76\" text-anchor=\"end\" fill=\"#a09060\" font-size=\"11\" font-family=\"Georgia,serif\">Wu-Tang</text>\n<rect x=\"160\" y=\"63\" width=\"395\" height=\"16\" fill=\"#c8a84a\" opacity=\"0.85\"/>\n<text x=\"561\" y=\"76\" fill=\"#c8a84a\" font-size=\"11\" font-family=\"Georgia,serif\">+97</text>\n<text x=\"154\" y=\"104\" text-anchor=\"end\" fill=\"#a09060\" font-size=\"11\" font-family=\"Georgia,serif\">Vacation Steve</text>\n<rect x=\"160\" y=\"91\" width=\"195\" height=\"16\" fill=\"#c8a84a\" opacity=\"0.85\"/>\n<text x=\"361\" y=\"104\" fill=\"#c8a84a\" font-size=\"11\" font-family=\"Georgia,serif\">+48</text>\n<text x=\"154\" y=\"132\" text-anchor=\"end\" fill=\"#a09060\" font-size=\"11\" font-family=\"Georgia,serif\">Vacation Albert</text>\n<rect x=\"160\" y=\"119\" width=\"163\" height=\"16\" fill=\"#c8a84a\" opacity=\"0.85\"/>\n<text x=\"329\" y=\"132\" fill=\"#c8a84a\" font-size=\"11\" font-family=\"Georgia,serif\">+40</text>\n<text x=\"154\" y=\"160\" text-anchor=\"end\" fill=\"#a09060\" font-size=\"11\" font-family=\"Georgia,serif\">Blood Captain</text>\n<rect x=\"160\" y=\"147\" width=\"114\" height=\"16\" fill=\"#c8a84a\" opacity=\"0.85\"/>\n<text x=\"280\" y=\"160\" fill=\"#c8a84a\" font-size=\"11\" font-family=\"Georgia,serif\">+28</text>\n<text x=\"154\" y=\"188\" text-anchor=\"end\" fill=\"#a09060\" font-size=\"11\" font-family=\"Georgia,serif\">Donald Trump</text>\n<rect x=\"160\" y=\"175\" width=\"81\" height=\"16\" fill=\"#c8a84a\" opacity=\"0.85\"/>\n<text x=\"247\" y=\"188\" fill=\"#c8a84a\" font-size=\"11\" font-family=\"Georgia,serif\">+20</text>\n<text x=\"154\" y=\"216\" text-anchor=\"end\" fill=\"#a09060\" font-size=\"11\" font-family=\"Georgia,serif\">Cokro</text>\n<rect x=\"160\" y=\"203\" width=\"73\" height=\"16\" fill=\"#c8a84a\" opacity=\"0.85\"/>\n<text x=\"239\" y=\"216\" fill=\"#c8a84a\" font-size=\"11\" font-family=\"Georgia,serif\">+18</text>\n<text x=\"154\" y=\"244\" text-anchor=\"end\" fill=\"#a09060\" font-size=\"11\" font-family=\"Georgia,serif\">SCRIPTUS</text>\n<rect x=\"160\" y=\"231\" width=\"73\" height=\"16\" fill=\"#c8a84a\" opacity=\"0.85\"/>\n<text x=\"239\" y=\"244\" fill=\"#c8a84a\" font-size=\"11\" font-family=\"Georgia,serif\">+18</text>\n</svg>\n\n\n<p><strong>POLICE BLOTTER</strong></p>\n\n<p><em>• Officers report that Flash Gordon was spotted streaking through the warehouse district at midnight, though whether this constitutes heroism or public indecency remains under investigation...</em></p>\n\n<p><em>• John James Rambo was arrested for disturbing the peace after attempting to liberate a speakeasy using only a butter knife and patriotic speeches...</em></p>\n\n<p><em>• Local precinct warns citizens to avoid Floyd's Barber Shop, as the proprietor has been \"giving customers more than just a close shave,\" according to Detective Murphy's incident report...</em></p>\n<svg xmlns=\"http://www.w3.org/2000/svg\" width=\"640\" height=\"276\" style=\"font-family:Georgia,serif;background:#0a0800;display:block;margin:18px auto\">\n<text x=\"320\" y=\"22\" text-anchor=\"middle\" fill=\"#c8a84a\" font-size=\"13\" font-weight=\"bold\" letter-spacing=\"2\" font-family=\"Georgia,serif\">HEAVIEST LOSSES THIS WEEK</text>\n<line x1=\"20\" y1=\"28\" x2=\"620\" y2=\"28\" stroke=\"#3a2a00\" stroke-width=\"1\"/>\n<text x=\"154\" y=\"48\" text-anchor=\"end\" fill=\"#a09060\" font-size=\"11\" font-family=\"Georgia,serif\">StreetKing</text>\n<rect x=\"160\" y=\"35\" width=\"400\" height=\"16\" fill=\"#8b1a1a\" opacity=\"0.85\"/>\n<text x=\"566\" y=\"48\" fill=\"#8b1a1a\" font-size=\"11\" font-family=\"Georgia,serif\">-27</text>\n<text x=\"154\" y=\"76\" text-anchor=\"end\" fill=\"#a09060\" font-size=\"11\" font-family=\"Georgia,serif\">FIFTH BLOOD EMPEROR</text>\n<rect x=\"160\" y=\"63\" width=\"325\" height=\"16\" fill=\"#8b1a1a\" opacity=\"0.85\"/>\n<text x=\"491\" y=\"76\" fill=\"#8b1a1a\" font-size=\"11\" font-family=\"Georgia,serif\">-22</text>\n<text x=\"154\" y=\"104\" text-anchor=\"end\" fill=\"#a09060\" font-size=\"11\" font-family=\"Georgia,serif\">vortex</text>\n<rect x=\"160\" y=\"91\" width=\"311\" height=\"16\" fill=\"#8b1a1a\" opacity=\"0.85\"/>\n<text x=\"477\" y=\"104\" fill=\"#8b1a1a\" font-size=\"11\" font-family=\"Georgia,serif\">-21</text>\n<text x=\"154\" y=\"132\" text-anchor=\"end\" fill=\"#a09060\" font-size=\"11\" font-family=\"Georgia,serif\">Ustaz Ice</text>\n<rect x=\"160\" y=\"119\" width=\"311\" height=\"16\" fill=\"#8b1a1a\" opacity=\"0.85\"/>\n<text x=\"477\" y=\"132\" fill=\"#8b1a1a\" font-size=\"11\" font-family=\"Georgia,serif\">-21</text>\n<text x=\"154\" y=\"160\" text-anchor=\"end\" fill=\"#a09060\" font-size=\"11\" font-family=\"Georgia,serif\">Way6444</text>\n<rect x=\"160\" y=\"147\" width=\"296\" height=\"16\" fill=\"#8b1a1a\" opacity=\"0.85\"/>\n<text x=\"462\" y=\"160\" fill=\"#8b1a1a\" font-size=\"11\" font-family=\"Georgia,serif\">-20</text>\n<text x=\"154\" y=\"188\" text-anchor=\"end\" fill=\"#a09060\" font-size=\"11\" font-family=\"Georgia,serif\">snakeeyes</text>\n<rect x=\"160\" y=\"175\" width=\"177\" height=\"16\" fill=\"#8b1a1a\" opacity=\"0.85\"/>\n<text x=\"343\" y=\"188\" fill=\"#8b1a1a\" font-size=\"11\" font-family=\"Georgia,serif\">-12</text>\n<text x=\"154\" y=\"216\" text-anchor=\"end\" fill=\"#a09060\" font-size=\"11\" font-family=\"Georgia,serif\">Nabru</text>\n<rect x=\"160\" y=\"203\" width=\"74\" height=\"16\" fill=\"#8b1a1a\" opacity=\"0.85\"/>\n<text x=\"240\" y=\"216\" fill=\"#8b1a1a\" font-size=\"11\" font-family=\"Georgia,serif\">-5</text>\n<text x=\"154\" y=\"244\" text-anchor=\"end\" fill=\"#a09060\" font-size=\"11\" font-family=\"Georgia,serif\">Lusitanio</text>\n<rect x=\"160\" y=\"231\" width=\"59\" height=\"16\" fill=\"#8b1a1a\" opacity=\"0.85\"/>\n<text x=\"225\" y=\"244\" fill=\"#8b1a1a\" font-size=\"11\" font-family=\"Georgia,serif\">-4</text>\n</svg>\n<hr>\n<svg xmlns=\"http://www.w3.org/2000/svg\" width=\"640\" height=\"143\" style=\"font-family:Georgia,serif;background:#0a0800;display:block;margin:18px auto\">\n<text x=\"320\" y=\"22\" text-anchor=\"middle\" fill=\"#c8a84a\" font-size=\"13\" font-weight=\"bold\" letter-spacing=\"2\" font-family=\"Georgia,serif\">HQ RAIDS — TOP ATTACKERS</text>\n<line x1=\"20\" y1=\"30\" x2=\"620\" y2=\"30\" stroke=\"#3a2a00\" stroke-width=\"1\"/>\n<text x=\"148\" y=\"53\" text-anchor=\"end\" fill=\"#a09060\" font-size=\"11\" font-family=\"Georgia,serif\">Wu-Tang</text>\n<polygon points=\"156,43 161,48 156,53 151,48\" fill=\"#8b1a1a\"/>\n<rect x=\"170\" y=\"41\" width=\"410\" height=\"14\" fill=\"#6b1010\" opacity=\"0.9\" rx=\"1\"/>\n<rect x=\"577\" y=\"41\" width=\"3\" height=\"14\" fill=\"#c03030\"/>\n<text x=\"588\" y=\"53\" fill=\"#c04040\" font-size=\"12\" font-weight=\"bold\" font-family=\"Georgia,serif\">17✕</text>\n<text x=\"148\" y=\"82\" text-anchor=\"end\" fill=\"#a09060\" font-size=\"11\" font-family=\"Georgia,serif\">Sir Caprice</text>\n<polygon points=\"156,72 161,77 156,82 151,77\" fill=\"#8b1a1a\"/>\n<rect x=\"170\" y=\"70\" width=\"313\" height=\"14\" fill=\"#6b1010\" opacity=\"0.9\" rx=\"1\"/>\n<rect x=\"480\" y=\"70\" width=\"3\" height=\"14\" fill=\"#c03030\"/>\n<text x=\"491\" y=\"82\" fill=\"#c04040\" font-size=\"12\" font-weight=\"bold\" font-family=\"Georgia,serif\">13✕</text>\n<text x=\"148\" y=\"111\" text-anchor=\"end\" fill=\"#a09060\" font-size=\"11\" font-family=\"Georgia,serif\">Vacation Bob</text>\n<polygon points=\"156,101 161,106 156,111 151,106\" fill=\"#8b1a1a\"/>\n<rect x=\"170\" y=\"99\" width=\"24\" height=\"14\" fill=\"#6b1010\" opacity=\"0.9\" rx=\"1\"/>\n<rect x=\"191\" y=\"99\" width=\"3\" height=\"14\" fill=\"#c03030\"/>\n<text x=\"202\" y=\"111\" fill=\"#c04040\" font-size=\"12\" font-weight=\"bold\" font-family=\"Georgia,serif\">1✕</text>\n</svg>","stats":{"total_tiles_start":20743,"total_tiles_end":20977,"hq_captures":31,"raids":500,"total_cash_looted":28641.71,"newcomers":6,"vanished":45,"top_gainer":"Sir Caprice","top_gainer_net":98}}